<?xml version = '1.0' encoding = 'UTF-8'?>
<Diagram class="oracle.dbtools.crest.swingui.logical.DPVLogical" name="Logical" id="FEA851A4-C68E-A249-26E6-AEA4876AD3E2">
<createdBy>cbern</createdBy>
<modifiedBy>cbern</modifiedBy>
<createdTime>2024-09-11 02:53:03 UTC</createdTime>
<autoRoute>false</autoRoute>
<boxInbox>true</boxInbox>
<showLegend>false</showLegend>
<showLabels>false</showLabels>
<showRelAttributes>false</showRelAttributes>
<gridEnabled>false</gridEnabled>
<showGrid>false</showGrid>
<diagramColor>-1</diagramColor>
<display>false</display>
<notation>1</notation>
<objectViews>
<OView class="oracle.dbtools.crest.swingui.logical.TVEntity" oid="28B8A8ED-4148-BD6E-C9E4-E70995077A48" otype="Entity" vid="3003443A-20F9-BBCE-60BF-EF79E33A082D">
<hideElementsInCurrentOnly>false</hideElementsInCurrentOnly>
<bounds x="436" y="378" width="170" height="166"/>
</OView>
<OView class="oracle.dbtools.crest.swingui.logical.TVEntity" oid="314C42A3-7B16-164A-681D-0E235500443F" otype="Entity" vid="809AFFA6-6BDD-EEDB-65F0-B9CA30C240EB">
<hideElementsInCurrentOnly>false</hideElementsInCurrentOnly>
<bounds x="705" y="461" width="170" height="110"/>
</OView>
<OView class="oracle.dbtools.crest.swingui.logical.TVEntity" oid="4C020FED-D3D3-DB87-590F-C06F96ADE2CA" otype="Entity" vid="6BDA7986-681C-F4C3-7404-8557F8844A76">
<hideElementsInCurrentOnly>false</hideElementsInCurrentOnly>
<bounds x="439" y="215" width="170" height="110"/>
</OView>
<OView class="oracle.dbtools.crest.swingui.logical.TVEntity" oid="70400727-9328-5F83-3C3C-4595AEDCB5AA" otype="Entity" vid="F5647638-057F-9289-C867-B7E62A087D06">
<hideElementsInCurrentOnly>false</hideElementsInCurrentOnly>
<bounds x="159" y="63" width="170" height="78"/>
</OView>
<OView class="oracle.dbtools.crest.swingui.logical.TVEntity" oid="A3855DA3-96CF-7E84-E3C1-A08732D29454" otype="Entity" vid="B6A30A30-21CB-0A1B-B826-F25586D34F0B">
<hideElementsInCurrentOnly>false</hideElementsInCurrentOnly>
<bounds x="151" y="215" width="170" height="110"/>
</OView>
<OView class="oracle.dbtools.crest.swingui.logical.TVEntity" oid="C8D9D68B-235A-EF99-5C6E-A92B3FA53BE5" otype="Entity" vid="11AB9E59-0929-D6FD-A2CF-7973858A323A">
<hideElementsInCurrentOnly>false</hideElementsInCurrentOnly>
<bounds x="704" y="336" width="170" height="110"/>
</OView>
<OView class="oracle.dbtools.crest.swingui.logical.TVEntity" oid="DFAF9C15-BB74-F47B-EAA9-A2677FB8CB63" otype="Entity" vid="72DF4AEF-4FB9-F0CB-1A52-F846D19A242D">
<hideElementsInCurrentOnly>false</hideElementsInCurrentOnly>
<bounds x="155" y="409" width="170" height="110"/>
</OView>
</objectViews>
<connectors>
<Connector class="oracle.dbtools.crest.swingui.logical.TVRelation" oid="0142F86B-7C7D-C480-DEB7-1661FDD5F968" otype="Relation" vid_source="6BDA7986-681C-F4C3-7404-8557F8844A76" vid_target="B6A30A30-21CB-0A1B-B826-F25586D34F0B">
<hideElementsInCurrentOnly>false</hideElementsInCurrentOnly>
<backgroundColor>-16777216</backgroundColor>
<lineWidth>1</lineWidth>
<points>
<point x="439" y="270"/>
<point x="321" y="270"/>
</points>
</Connector>
<Connector class="oracle.dbtools.crest.swingui.logical.TVRelation" oid="1B4CDDEE-186A-68E5-C999-F48B91A53807" otype="Relation" vid_source="B6A30A30-21CB-0A1B-B826-F25586D34F0B" vid_target="72DF4AEF-4FB9-F0CB-1A52-F846D19A242D">
<hideElementsInCurrentOnly>false</hideElementsInCurrentOnly>
<backgroundColor>-16777216</backgroundColor>
<lineWidth>1</lineWidth>
<points>
<point x="238" y="325"/>
<point x="238" y="409"/>
</points>
</Connector>
<Connector class="oracle.dbtools.crest.swingui.logical.TVRelation" oid="34DC0A8E-C74D-221E-C3B2-F1196311D2B0" otype="Relation" vid_source="11AB9E59-0929-D6FD-A2CF-7973858A323A" vid_target="3003443A-20F9-BBCE-60BF-EF79E33A082D">
<hideElementsInCurrentOnly>false</hideElementsInCurrentOnly>
<backgroundColor>-16777216</backgroundColor>
<lineWidth>1</lineWidth>
<points>
<point x="704" y="412"/>
<point x="606" y="412"/>
</points>
</Connector>
<Connector class="oracle.dbtools.crest.swingui.logical.TVRelation" oid="7C2B55A8-2B4D-E7C8-883A-62BE8D6F2DCD" otype="Relation" vid_source="3003443A-20F9-BBCE-60BF-EF79E33A082D" vid_target="72DF4AEF-4FB9-F0CB-1A52-F846D19A242D">
<hideElementsInCurrentOnly>false</hideElementsInCurrentOnly>
<backgroundColor>-16777216</backgroundColor>
<lineWidth>1</lineWidth>
<points>
<point x="436" y="464"/>
<point x="325" y="464"/>
</points>
</Connector>
<Connector class="oracle.dbtools.crest.swingui.logical.TVRelation" oid="BF510109-38B2-4AED-593D-4CE6FA07A9AF" otype="Relation" vid_source="809AFFA6-6BDD-EEDB-65F0-B9CA30C240EB" vid_target="3003443A-20F9-BBCE-60BF-EF79E33A082D">
<hideElementsInCurrentOnly>false</hideElementsInCurrentOnly>
<backgroundColor>-16777216</backgroundColor>
<lineWidth>1</lineWidth>
<points>
<point x="705" y="502"/>
<point x="606" y="502"/>
</points>
</Connector>
<Connector class="oracle.dbtools.crest.swingui.logical.TVRelation" oid="C5B2F2BB-0EAD-1DE8-B32D-40B24C777140" otype="Relation" vid_source="F5647638-057F-9289-C867-B7E62A087D06" vid_target="B6A30A30-21CB-0A1B-B826-F25586D34F0B">
<hideElementsInCurrentOnly>false</hideElementsInCurrentOnly>
<backgroundColor>-16777216</backgroundColor>
<lineWidth>1</lineWidth>
<points>
<point x="240" y="141"/>
<point x="240" y="173"/>
<point x="240" y="215"/>
</points>
</Connector>
</connectors>
</Diagram>